MANIFEST.in
README
requirements.txt
setup.py
ajenti.plugin.terminal.egg-info/PKG-INFO
ajenti.plugin.terminal.egg-info/SOURCES.txt
ajenti.plugin.terminal.egg-info/dependency_links.txt
ajenti.plugin.terminal.egg-info/requires.txt
ajenti.plugin.terminal.egg-info/top_level.txt
ajenti_plugin_terminal/README.md
ajenti_plugin_terminal/__init__.py
ajenti_plugin_terminal/bower.json
ajenti_plugin_terminal/main.py
ajenti_plugin_terminal/manager.py
ajenti_plugin_terminal/plugin.yml
ajenti_plugin_terminal/requirements.txt
ajenti_plugin_terminal/terminal.py
ajenti_plugin_terminal/views.py
ajenti_plugin_terminal/widget.py
ajenti_plugin_terminal/locale/app.pot
ajenti_plugin_terminal/locale/af/LC_MESSAGES/app.js
ajenti_plugin_terminal/locale/af/LC_MESSAGES/app.po
ajenti_plugin_terminal/locale/af/LC_MESSAGES/app.po~
ajenti_plugin_terminal/locale/ar/LC_MESSAGES/app.js
ajenti_plugin_terminal/locale/ar/LC_MESSAGES/app.po
ajenti_plugin_terminal/locale/ar/LC_MESSAGES/app.po~
ajenti_plugin_terminal/locale/be/LC_MESSAGES/app.js
ajenti_plugin_terminal/locale/be/LC_MESSAGES/app.po
ajenti_plugin_terminal/locale/be/LC_MESSAGES/app.po~
ajenti_plugin_terminal/locale/bg/LC_MESSAGES/app.js
ajenti_plugin_terminal/locale/bg/LC_MESSAGES/app.po
ajenti_plugin_terminal/locale/bg/LC_MESSAGES/app.po~
ajenti_plugin_terminal/locale/bn/LC_MESSAGES/app.js
ajenti_plugin_terminal/locale/bn/LC_MESSAGES/app.po
ajenti_plugin_terminal/locale/bn/LC_MESSAGES/app.po~
ajenti_plugin_terminal/locale/bs/LC_MESSAGES/app.js
ajenti_plugin_terminal/locale/bs/LC_MESSAGES/app.po
ajenti_plugin_terminal/locale/ca/LC_MESSAGES/app.js
ajenti_plugin_terminal/locale/ca/LC_MESSAGES/app.po
ajenti_plugin_terminal/locale/ca/LC_MESSAGES/app.po~
ajenti_plugin_terminal/locale/cs/LC_MESSAGES/app.js
ajenti_plugin_terminal/locale/cs/LC_MESSAGES/app.po
ajenti_plugin_terminal/locale/cs/LC_MESSAGES/app.po~
ajenti_plugin_terminal/locale/da/LC_MESSAGES/app.js
ajenti_plugin_terminal/locale/da/LC_MESSAGES/app.po
ajenti_plugin_terminal/locale/da/LC_MESSAGES/app.po~
ajenti_plugin_terminal/locale/de/LC_MESSAGES/app.js
ajenti_plugin_terminal/locale/de/LC_MESSAGES/app.po
ajenti_plugin_terminal/locale/de/LC_MESSAGES/app.po~
ajenti_plugin_terminal/locale/el/LC_MESSAGES/app.js
