Metadata-Version: 1.2
Name: ajenti.plugin.terminal
Version: 0.42
Summary: Terminal
Home-page: https://ajenti.org
Author: Ajenti project
Author-email: e@ajenti.org
License: UNKNOWN
Platform: UNKNOWN
Requires-Python: >=3
